{"res":{"70002.png":{"x":0,"y":185,"w":43,"h":92},"70000.png":{"x":0,"y":0,"w":43,"h":92},"70001.png":{"x":0,"y":92,"w":43,"h":93},"70006.png":{"x":43,"y":0,"w":43,"h":90},"70005.png":{"x":0,"y":477,"w":44,"h":109},"70004.png":{"x":0,"y":369,"w":43,"h":108},"70003.png":{"x":0,"y":277,"w":43,"h":92}},"mc":{"5000032_c_7":{"frames":[{"res":"70000.png","y":-82,"x":-31},{"res":"70001.png","y":-83,"x":-31},{"res":"70002.png","y":-82,"x":-31},{"res":"70003.png","y":-82,"x":-31},{"res":"70004.png","y":-98,"x":-31},{"res":"70005.png","y":-99,"x":-31},{"res":"70006.png","y":-80,"x":-31}],"frameRate":15}}}