{"res":{"80006.png":{"x":172,"y":0,"w":51,"h":84},"80002.png":{"x":117,"y":0,"w":55,"h":88},"80001.png":{"x":59,"y":0,"w":58,"h":86},"80000.png":{"x":0,"y":0,"w":59,"h":86},"80005.png":{"x":0,"y":173,"w":51,"h":104},"80004.png":{"x":54,"y":86,"w":53,"h":103},"80003.png":{"x":0,"y":86,"w":54,"h":87}},"mc":{"5201032_c_8":{"frames":[{"res":"80000.png","y":-84,"x":-35},{"res":"80001.png","y":-84,"x":-37},{"res":"80002.png","y":-86,"x":-38},{"res":"80003.png","y":-85,"x":-37},{"res":"80004.png","y":-101,"x":-36},{"res":"80005.png","y":-102,"x":-34},{"res":"80006.png","y":-82,"x":-34}],"frameRate":15}}}