{"res":{"40005.png":{"x":186,"y":0,"w":59,"h":87},"40006.png":{"x":245,"y":0,"w":63,"h":93},"40003.png":{"x":0,"y":85,"w":56,"h":86},"40004.png":{"x":56,"y":85,"w":53,"h":81},"40007.png":{"x":186,"y":87,"w":53,"h":88},"40002.png":{"x":116,"y":0,"w":70,"h":91},"40001.png":{"x":49,"y":0,"w":67,"h":85},"40000.png":{"x":0,"y":0,"w":49,"h":83}},"mc":{"5201031_r_4":{"frames":[{"res":"40000.png","y":-82,"x":-20},{"res":"40001.png","y":-83,"x":-33},{"res":"40002.png","y":-82,"x":-38},{"res":"40003.png","y":-80,"x":-29},{"res":"40004.png","y":-82,"x":-27},{"res":"40005.png","y":-83,"x":-28},{"res":"40006.png","y":-82,"x":-32},{"res":"40007.png","y":-80,"x":-26}],"frameRate":15}}}