{"res":{"20001.png":{"x":0,"y":119,"w":59,"h":111},"20005.png":{"x":59,"y":114,"w":84,"h":110},"20004.png":{"x":199,"y":0,"w":94,"h":120},"20003.png":{"x":133,"y":0,"w":66,"h":114},"20000.png":{"x":0,"y":0,"w":49,"h":119},"20002.png":{"x":49,"y":0,"w":84,"h":96},"20006.png":{"x":293,"y":0,"w":83,"h":112}},"mc":{"5206031_a_2":{"frames":[{"res":"20000.png","y":-95,"x":-24},{"res":"20001.png","y":-86,"x":-34},{"res":"20002.png","y":-70,"x":-58},{"res":"20003.png","y":-91,"x":-37},{"res":"20004.png","y":-92,"x":-37},{"res":"20005.png","y":-85,"x":-36},{"res":"20006.png","y":-85,"x":-34}],"frameRate":15}}}