{"res":{"30004.png":{"x":271,"y":0,"w":61,"h":87},"30001.png":{"x":57,"y":0,"w":73,"h":90},"30007.png":{"x":210,"y":85,"w":61,"h":88},"30005.png":{"x":130,"y":86,"w":74,"h":88},"30002.png":{"x":130,"y":0,"w":80,"h":86},"30003.png":{"x":210,"y":0,"w":61,"h":85},"30006.png":{"x":0,"y":92,"w":81,"h":88},"30000.png":{"x":0,"y":0,"w":57,"h":92}},"mc":{"5301031_r_3":{"frames":[{"res":"30000.png","y":-85,"x":-34},{"res":"30001.png","y":-87,"x":-41},{"res":"30002.png","y":-86,"x":-48},{"res":"30003.png","y":-84,"x":-36},{"res":"30004.png","y":-85,"x":-38},{"res":"30005.png","y":-87,"x":-41},{"res":"30006.png","y":-85,"x":-48},{"res":"30007.png","y":-84,"x":-36}],"frameRate":15}}}