{"res":{"20007.png":{"x":0,"y":190,"w":90,"h":88},"20006.png":{"x":94,"y":104,"w":76,"h":91},"20004.png":{"x":295,"y":0,"w":76,"h":94},"20001.png":{"x":102,"y":0,"w":99,"h":104},"20003.png":{"x":201,"y":0,"w":94,"h":89},"20000.png":{"x":0,"y":0,"w":102,"h":96},"20005.png":{"x":201,"y":89,"w":68,"h":101},"20002.png":{"x":0,"y":96,"w":94,"h":94}},"mc":{"5302031_r_2":{"frames":[{"res":"20000.png","y":-89,"x":-73},{"res":"20001.png","y":-91,"x":-67},{"res":"20002.png","y":-89,"x":-63},{"res":"20003.png","y":-88,"x":-67},{"res":"20004.png","y":-89,"x":-55},{"res":"20005.png","y":-91,"x":-45},{"res":"20006.png","y":-89,"x":-51},{"res":"20007.png","y":-88,"x":-70}],"frameRate":15}}}