{"res":{"60004.png":{"x":0,"y":107,"w":67,"h":105},"60000.png":{"x":0,"y":0,"w":71,"h":107},"60006.png":{"x":287,"y":106,"w":83,"h":111},"60003.png":{"x":71,"y":105,"w":68,"h":103},"60002.png":{"x":142,"y":0,"w":74,"h":106},"60007.png":{"x":139,"y":110,"w":78,"h":109},"60005.png":{"x":216,"y":0,"w":71,"h":110},"60001.png":{"x":71,"y":0,"w":71,"h":105}},"mc":{"5305031_r_6":{"frames":[{"res":"60000.png","y":-88,"x":-39},{"res":"60001.png","y":-89,"x":-37},{"res":"60002.png","y":-88,"x":-36},{"res":"60003.png","y":-86,"x":-32},{"res":"60004.png","y":-88,"x":-32},{"res":"60005.png","y":-91,"x":-32},{"res":"60006.png","y":-91,"x":-38},{"res":"60007.png","y":-88,"x":-41}],"frameRate":15}}}