{"res":{"10001.png":{"x":67,"y":0,"w":62,"h":114},"10006.png":{"x":0,"y":119,"w":64,"h":108},"10004.png":{"x":67,"y":114,"w":76,"h":126},"10002.png":{"x":129,"y":0,"w":67,"h":97},"10005.png":{"x":265,"y":0,"w":71,"h":110},"10003.png":{"x":196,"y":0,"w":69,"h":118},"10000.png":{"x":0,"y":0,"w":67,"h":119}},"mc":{"5308031_a_1":{"frames":[{"res":"10000.png","y":-97,"x":-32},{"res":"10001.png","y":-92,"x":-32},{"res":"10002.png","y":-74,"x":-34},{"res":"10003.png","y":-98,"x":-37},{"res":"10004.png","y":-108,"x":-43},{"res":"10005.png","y":-93,"x":-34},{"res":"10006.png","y":-91,"x":-28}],"frameRate":15}}}