{"res":{"70004.png":{"x":185,"y":111,"w":89,"h":114},"70003.png":{"x":277,"y":0,"w":87,"h":112},"70001.png":{"x":94,"y":0,"w":91,"h":113},"70006.png":{"x":91,"y":113,"w":93,"h":117},"70007.png":{"x":364,"y":0,"w":93,"h":113},"70000.png":{"x":0,"y":0,"w":94,"h":113},"70005.png":{"x":0,"y":113,"w":91,"h":118},"70002.png":{"x":185,"y":0,"w":92,"h":111}},"mc":{"5308031_r_7":{"frames":[{"res":"70000.png","y":-100,"x":-39},{"res":"70001.png","y":-100,"x":-39},{"res":"70002.png","y":-98,"x":-38},{"res":"70003.png","y":-97,"x":-31},{"res":"70004.png","y":-100,"x":-33},{"res":"70005.png","y":-103,"x":-39},{"res":"70006.png","y":-102,"x":-39},{"res":"70007.png","y":-100,"x":-37}],"frameRate":15}}}