{"res":{"10005.png":{"x":263,"y":0,"w":71,"h":111},"10000.png":{"x":0,"y":0,"w":70,"h":122},"10002.png":{"x":134,"y":0,"w":61,"h":101},"10004.png":{"x":70,"y":114,"w":84,"h":123},"10006.png":{"x":0,"y":122,"w":70,"h":108},"10001.png":{"x":70,"y":0,"w":64,"h":114},"10003.png":{"x":195,"y":0,"w":68,"h":118}},"mc":{"5309031_a_1":{"frames":[{"res":"10000.png","y":-100,"x":-36},{"res":"10001.png","y":-93,"x":-34},{"res":"10002.png","y":-79,"x":-35},{"res":"10003.png","y":-98,"x":-35},{"res":"10004.png","y":-106,"x":-44},{"res":"10005.png","y":-95,"x":-34},{"res":"10006.png","y":-91,"x":-34}],"frameRate":15}}}