{"res":{"70003.png":{"x":249,"y":0,"w":72,"h":115},"70002.png":{"x":161,"y":0,"w":88,"h":99},"70005.png":{"x":321,"y":0,"w":91,"h":74},"70000.png":{"x":0,"y":0,"w":80,"h":105},"70001.png":{"x":80,"y":0,"w":81,"h":104},"70006.png":{"x":412,"y":0,"w":83,"h":85},"70004.png":{"x":80,"y":104,"w":89,"h":96}},"mc":{"5310032_a_7":{"frames":[{"res":"70000.png","y":-89,"x":-41},{"res":"70001.png","y":-88,"x":-45},{"res":"70002.png","y":-83,"x":-35},{"res":"70003.png","y":-99,"x":-41},{"res":"70004.png","y":-81,"x":-60},{"res":"70005.png","y":-58,"x":-62},{"res":"70006.png","y":-69,"x":-54}],"frameRate":15}}}