{"res":{"30002.png":{"x":212,"y":0,"w":102,"h":132},"30000.png":{"x":0,"y":0,"w":108,"h":133},"30001.png":{"x":108,"y":0,"w":104,"h":131},"30006.png":{"x":409,"y":0,"w":97,"h":132},"30005.png":{"x":314,"y":0,"w":95,"h":131},"30004.png":{"x":0,"y":133,"w":96,"h":131},"30003.png":{"x":108,"y":131,"w":99,"h":133}},"mc":{"5312032_c_3":{"frames":[{"res":"30000.png","y":-107,"x":-45},{"res":"30001.png","y":-107,"x":-43},{"res":"30002.png","y":-108,"x":-42},{"res":"30003.png","y":-109,"x":-40},{"res":"30004.png","y":-110,"x":-40},{"res":"30005.png","y":-109,"x":-40},{"res":"30006.png","y":-107,"x":-41}],"frameRate":15}}}