{"res":{"30005.png":{"x":43,"y":25,"w":16,"h":61},"30001.png":{"x":63,"y":0,"w":38,"h":54},"30002.png":{"x":0,"y":25,"w":15,"h":60},"30006.png":{"x":0,"y":85,"w":10,"h":61},"30004.png":{"x":20,"y":25,"w":23,"h":54},"30000.png":{"x":0,"y":0,"w":63,"h":25},"30003.png":{"x":15,"y":25,"w":5,"h":62}},"mc":{"5001012_c_3":{"frames":[{"y":-60,"res":"30000.png","x":10},{"y":-94,"res":"30001.png","x":18},{"y":-114,"res":"30002.png","x":19},{"y":-126,"res":"30003.png","x":18},{"y":-139,"res":"30004.png","x":-13},{"y":-137,"res":"30005.png","x":-1},{"y":-108,"res":"30006.png","x":17}],"frameRate":15}}}