{"res":{"40005.png":{"x":310,"y":0,"w":78,"h":87},"40004.png":{"x":232,"y":0,"w":78,"h":52},"40007.png":{"x":155,"y":87,"w":76,"h":58},"40003.png":{"x":155,"y":0,"w":77,"h":69},"40006.png":{"x":232,"y":52,"w":67,"h":98},"40001.png":{"x":83,"y":0,"w":72,"h":93},"40000.png":{"x":0,"y":0,"w":83,"h":62},"40002.png":{"x":0,"y":62,"w":72,"h":91}},"mc":{"5002012_r_4":{"frames":[{"y":-53,"res":"40000.png","x":-42},{"y":-80,"res":"40001.png","x":-43},{"y":-79,"res":"40002.png","x":-45},{"y":-58,"res":"40003.png","x":-42},{"y":-59,"res":"40004.png","x":-32},{"y":-97,"res":"40005.png","x":-17},{"y":-99,"res":"40006.png","x":-11},{"y":-74,"res":"40007.png","x":-28}],"frameRate":15}}}