{"res":{"60006.png":{"x":66,"y":78,"w":40,"h":82},"60002.png":{"x":0,"y":62,"w":33,"h":90},"60005.png":{"x":0,"y":152,"w":20,"h":113},"60000.png":{"x":0,"y":0,"w":74,"h":62},"60004.png":{"x":106,"y":0,"w":53,"h":132},"60001.png":{"x":74,"y":0,"w":32,"h":78},"60003.png":{"x":33,"y":62,"w":33,"h":104}},"mc":{"5105011_c_6":{"frames":[{"y":-80,"res":"60000.png","x":-57},{"y":-89,"res":"60001.png","x":-40},{"y":-102,"res":"60002.png","x":-35},{"y":-121,"res":"60003.png","x":-26},{"y":-167,"res":"60004.png","x":-29},{"y":-147,"res":"60005.png","x":-18},{"y":-93,"res":"60006.png","x":-46}],"frameRate":15}}}