{"res":{"40001.png":{"x":59,"y":0,"w":56,"h":75},"40005.png":{"x":88,"y":75,"w":19,"h":91},"40002.png":{"x":0,"y":46,"w":42,"h":93},"40004.png":{"x":42,"y":75,"w":46,"h":98},"40000.png":{"x":0,"y":0,"w":59,"h":46},"40006.png":{"x":88,"y":166,"w":53,"h":68},"40003.png":{"x":115,"y":0,"w":26,"h":98}},"mc":{"5106011_c_4":{"frames":[{"y":-70,"res":"40000.png","x":-13},{"y":-99,"res":"40001.png","x":-7},{"y":-122,"res":"40002.png","x":-2},{"y":-144,"res":"40003.png","x":4},{"y":-173,"res":"40004.png","x":-39},{"y":-161,"res":"40005.png","x":0},{"y":-98,"res":"40006.png","x":-7}],"frameRate":15}}}