{"res":{"60001.png":{"x":0,"y":75,"w":47,"h":91},"60004.png":{"x":47,"y":87,"w":43,"h":52},"60006.png":{"x":147,"y":0,"w":76,"h":60},"60000.png":{"x":0,"y":0,"w":34,"h":75},"60002.png":{"x":0,"y":166,"w":53,"h":89},"60007.png":{"x":90,"y":58,"w":52,"h":39},"60005.png":{"x":76,"y":0,"w":71,"h":58},"60003.png":{"x":47,"y":0,"w":29,"h":87}},"mc":{"5109011_r_6":{"frames":[{"y":-102,"res":"60000.png","x":-49},{"y":-125,"res":"60001.png","x":-40},{"y":-122,"res":"60002.png","x":-39},{"y":-113,"res":"60003.png","x":-36},{"y":-85,"res":"60004.png","x":-51},{"y":-73,"res":"60005.png","x":-62},{"y":-72,"res":"60006.png","x":-65},{"y":-65,"res":"60007.png","x":-60}],"frameRate":15}}}