{"res":{"10006.png":{"x":0,"y":358,"w":10,"h":76},"10007.png":{"x":0,"y":434,"w":16,"h":102},"10005.png":{"x":25,"y":92,"w":11,"h":83},"10002.png":{"x":0,"y":180,"w":29,"h":75},"10003.png":{"x":25,"y":0,"w":26,"h":92},"10000.png":{"x":0,"y":0,"w":25,"h":100},"10004.png":{"x":0,"y":255,"w":26,"h":103},"10001.png":{"x":0,"y":100,"w":25,"h":80}},"mc":{"5109011_r_1":{"frames":[{"y":-139,"res":"10000.png","x":-4},{"y":-137,"res":"10001.png","x":-9},{"y":-131,"res":"10002.png","x":-14},{"y":-133,"res":"10003.png","x":-8},{"y":-135,"res":"10004.png","x":-4},{"y":-106,"res":"10005.png","x":11},{"y":-97,"res":"10006.png","x":12},{"y":-126,"res":"10007.png","x":6}],"frameRate":15}}}