{"res":{"20000.png":{"x":0,"y":0,"w":36,"h":67},"20001.png":{"x":36,"y":0,"w":78,"h":76},"20004.png":{"x":0,"y":76,"w":79,"h":33},"20005.png":{"x":114,"y":36,"w":66,"h":62},"20002.png":{"x":114,"y":0,"w":67,"h":36},"20006.png":{"x":260,"y":0,"w":80,"h":52},"20003.png":{"x":181,"y":0,"w":79,"h":80}},"mc":{"5110011_a_2":{"frames":[{"y":-94,"res":"20000.png","x":10},{"y":-94,"res":"20001.png","x":-24},{"y":-55,"res":"20002.png","x":-102},{"y":-90,"res":"20003.png","x":-64},{"y":-97,"res":"20004.png","x":-23},{"y":-88,"res":"20005.png","x":13},{"y":-76,"res":"20006.png","x":14}],"frameRate":15}}}