{"res":{"50006.png":{"x":0,"y":313,"w":47,"h":82},"50001.png":{"x":33,"y":0,"w":53,"h":82},"50004.png":{"x":0,"y":188,"w":39,"h":125},"50005.png":{"x":49,"y":82,"w":36,"h":104},"50003.png":{"x":0,"y":82,"w":49,"h":106},"50002.png":{"x":86,"y":0,"w":59,"h":98},"50000.png":{"x":0,"y":0,"w":33,"h":60}},"mc":{"5111011_c_5":{"frames":[{"y":-79,"res":"50000.png","x":-32},{"y":-105,"res":"50001.png","x":-29},{"y":-129,"res":"50002.png","x":-25},{"y":-153,"res":"50003.png","x":-14},{"y":-201,"res":"50004.png","x":-24},{"y":-174,"res":"50005.png","x":-16},{"y":-106,"res":"50006.png","x":-29}],"frameRate":15}}}