{"res":{"50001.png":{"x":110,"y":0,"w":109,"h":160},"50000.png":{"x":0,"y":0,"w":110,"h":143},"50006.png":{"x":84,"y":160,"w":133,"h":163},"50004.png":{"x":0,"y":143,"w":84,"h":138},"50005.png":{"x":219,"y":92,"w":77,"h":113},"50003.png":{"x":331,"y":0,"w":126,"h":146},"50002.png":{"x":219,"y":0,"w":112,"h":92}},"mc":{"5116012_a_5":{"frames":[{"y":-164,"res":"50000.png","x":-100},{"y":-186,"res":"50001.png","x":-95},{"y":-140,"res":"50002.png","x":-17},{"y":-195,"res":"50003.png","x":-51},{"y":-147,"res":"50004.png","x":-44},{"y":-14,"res":"50005.png","x":-31},{"y":-43,"res":"50006.png","x":-58}],"frameRate":15}}}