{"res":{"20003.png":{"x":178,"y":0,"w":75,"h":58},"20002.png":{"x":81,"y":0,"w":97,"h":44},"20000.png":{"x":0,"y":0,"w":47,"h":68},"20005.png":{"x":0,"y":68,"w":65,"h":34},"20006.png":{"x":146,"y":44,"w":32,"h":38},"20001.png":{"x":47,"y":0,"w":34,"h":61},"20004.png":{"x":81,"y":44,"w":65,"h":57}},"mc":{"5188012_a_2":{"frames":[{"y":-90,"res":"20000.png","x":11},{"y":-89,"res":"20001.png","x":-8},{"y":-60,"res":"20002.png","x":-115},{"y":-111,"res":"20003.png","x":-62},{"y":-125,"res":"20004.png","x":-8},{"y":-62,"res":"20005.png","x":23},{"y":-63,"res":"20006.png","x":27}],"frameRate":15}}}