{"res":{"10002.png":{"x":9,"y":0,"w":23,"h":38},"10006.png":{"x":15,"y":111,"w":54,"h":112},"10003.png":{"x":0,"y":111,"w":15,"h":73},"10001.png":{"x":0,"y":78,"w":23,"h":33},"10000.png":{"x":0,"y":0,"w":9,"h":78},"10005.png":{"x":0,"y":291,"w":52,"h":117},"10004.png":{"x":0,"y":184,"w":12,"h":107},"10007.png":{"x":69,"y":38,"w":26,"h":121}},"mc":{"5202012_r_1":{"frames":[{"y":-97,"res":"10000.png","x":12},{"y":-65,"res":"10001.png","x":5},{"y":-63,"res":"10002.png","x":3},{"y":-88,"res":"10003.png","x":8},{"y":-123,"res":"10004.png","x":7},{"y":-145,"res":"10005.png","x":-22},{"y":-141,"res":"10006.png","x":-22},{"y":-134,"res":"10007.png","x":-1}],"frameRate":15}}}