{"res":{"40002.png":{"x":0,"y":58,"w":50,"h":106},"40006.png":{"x":0,"y":174,"w":51,"h":118},"40004.png":{"x":172,"y":0,"w":51,"h":119},"40001.png":{"x":102,"y":0,"w":70,"h":86},"40005.png":{"x":99,"y":86,"w":51,"h":121},"40003.png":{"x":50,"y":58,"w":49,"h":116},"40000.png":{"x":0,"y":0,"w":102,"h":58}},"mc":{"5209012_c_4":{"frames":[{"y":-62,"res":"40000.png","x":-47},{"y":-91,"res":"40001.png","x":-23},{"y":-109,"res":"40002.png","x":1},{"y":-124,"res":"40003.png","x":-3},{"y":-152,"res":"40004.png","x":-32},{"y":-143,"res":"40005.png","x":-24},{"y":-108,"res":"40006.png","x":-14}],"frameRate":15}}}