{"res":{"80001.png":{"x":62,"y":0,"w":59,"h":121},"80005.png":{"x":222,"y":0,"w":103,"h":53},"80000.png":{"x":0,"y":0,"w":62,"h":120},"80004.png":{"x":173,"y":0,"w":49,"h":55},"80006.png":{"x":325,"y":0,"w":123,"h":40},"80002.png":{"x":0,"y":120,"w":48,"h":111},"80003.png":{"x":121,"y":0,"w":52,"h":52}},"mc":{"5210012_a_8":{"frames":[{"y":-121,"res":"80000.png","x":-5},{"y":-119,"res":"80001.png","x":9},{"y":-97,"res":"80002.png","x":6},{"y":-113,"res":"80003.png","x":-1},{"y":-126,"res":"80004.png","x":-43},{"y":-63,"res":"80005.png","x":-90},{"y":-61,"res":"80006.png","x":-80}],"frameRate":15}}}