{"res":{"40005.png":{"x":482,"y":0,"w":142,"h":127},"40001.png":{"x":129,"y":0,"w":92,"h":155},"40003.png":{"x":221,"y":0,"w":115,"h":129},"40006.png":{"x":336,"y":88,"w":134,"h":139},"40002.png":{"x":0,"y":104,"w":92,"h":156},"40000.png":{"x":0,"y":0,"w":129,"h":104},"40004.png":{"x":336,"y":0,"w":146,"h":88},"40007.png":{"x":92,"y":155,"w":147,"h":86}},"mc":{"5213011_r_4":{"frames":[{"y":-96,"res":"40000.png","x":-58},{"y":-126,"res":"40001.png","x":-26},{"y":-127,"res":"40002.png","x":-25},{"y":-109,"res":"40003.png","x":-46},{"y":-86,"res":"40004.png","x":-77},{"y":-107,"res":"40005.png","x":-86},{"y":-113,"res":"40006.png","x":-82},{"y":-75,"res":"40007.png","x":-81}],"frameRate":15}}}