{"res":{"60001.png":{"x":155,"y":0,"w":169,"h":170},"60003.png":{"x":501,"y":0,"w":167,"h":132},"60000.png":{"x":0,"y":0,"w":155,"h":134},"60004.png":{"x":0,"y":134,"w":151,"h":125},"60002.png":{"x":324,"y":0,"w":177,"h":170},"60006.png":{"x":501,"y":132,"w":128,"h":158},"60007.png":{"x":782,"y":0,"w":140,"h":142},"60005.png":{"x":668,"y":0,"w":114,"h":158}},"mc":{"5216012_r_6":{"frames":[{"y":-103,"res":"60000.png","x":-116},{"y":-133,"res":"60001.png","x":-106},{"y":-128,"res":"60002.png","x":-106},{"y":-94,"res":"60003.png","x":-124},{"y":-97,"res":"60004.png","x":-129},{"y":-162,"res":"60005.png","x":-84},{"y":-158,"res":"60006.png","x":-80},{"y":-136,"res":"60007.png","x":-109}],"frameRate":15}}}