{"res":{"70002.png":{"x":244,"y":0,"w":172,"h":209},"70001.png":{"x":128,"y":0,"w":116,"h":228},"70006.png":{"x":416,"y":141,"w":205,"h":139},"70003.png":{"x":416,"y":0,"w":181,"h":116},"70005.png":{"x":773,"y":0,"w":215,"h":141},"70004.png":{"x":597,"y":0,"w":176,"h":141},"70000.png":{"x":0,"y":0,"w":128,"h":226}},"mc":{"5217012_a_7":{"frames":[{"y":-209,"res":"70000.png","x":-43},{"y":-202,"res":"70001.png","x":-19},{"y":-151,"res":"70002.png","x":-30},{"y":-157,"res":"70003.png","x":-57},{"y":-163,"res":"70004.png","x":-109},{"y":-92,"res":"70005.png","x":-170},{"y":-96,"res":"70006.png","x":-166}],"frameRate":15}}}