{"res":{"60004.png":{"x":0,"y":155,"w":177,"h":148},"60000.png":{"x":0,"y":0,"w":190,"h":155},"60002.png":{"x":415,"y":0,"w":209,"h":174},"60006.png":{"x":624,"y":156,"w":138,"h":198},"60005.png":{"x":844,"y":0,"w":133,"h":177},"60003.png":{"x":624,"y":0,"w":220,"h":156},"60007.png":{"x":415,"y":177,"w":145,"h":154},"60001.png":{"x":190,"y":0,"w":225,"h":183}},"mc":{"5218012_r_6":{"frames":[{"y":-112,"res":"60000.png","x":-135},{"y":-128,"res":"60001.png","x":-133},{"y":-125,"res":"60002.png","x":-127},{"y":-115,"res":"60003.png","x":-139},{"y":-117,"res":"60004.png","x":-128},{"y":-151,"res":"60005.png","x":-96},{"y":-176,"res":"60006.png","x":-93},{"y":-132,"res":"60007.png","x":-111}],"frameRate":15}}}