{"res":{"60000.png":{"x":0,"y":0,"w":21,"h":99},"60005.png":{"x":132,"y":56,"w":63,"h":34},"60006.png":{"x":150,"y":0,"w":75,"h":37},"60002.png":{"x":21,"y":0,"w":55,"h":88},"60003.png":{"x":64,"y":88,"w":68,"h":45},"60004.png":{"x":76,"y":0,"w":74,"h":56},"60001.png":{"x":0,"y":99,"w":64,"h":51}},"mc":{"5306011_a_6":{"frames":[{"y":-149,"res":"60000.png","x":-33},{"y":-120,"res":"60001.png","x":-50},{"y":-90,"res":"60002.png","x":41},{"y":-99,"res":"60003.png","x":-8},{"y":-120,"res":"60004.png","x":-51},{"y":2,"res":"60005.png","x":-79},{"y":-6,"res":"60006.png","x":-94}],"frameRate":15}}}