{"res":{"60002.png":{"x":118,"y":0,"w":58,"h":63},"60004.png":{"x":0,"y":72,"w":45,"h":61},"60000.png":{"x":0,"y":0,"w":49,"h":72},"60001.png":{"x":49,"y":0,"w":69,"h":59},"60003.png":{"x":49,"y":59,"w":55,"h":58},"60005.png":{"x":176,"y":0,"w":53,"h":57},"60006.png":{"x":229,"y":0,"w":53,"h":61}},"mc":{"5311012_c_6":{"frames":[{"y":-82,"res":"60000.png","x":-62},{"y":-88,"res":"60001.png","x":-65},{"y":-98,"res":"60002.png","x":-42},{"y":-109,"res":"60003.png","x":-38},{"y":-145,"res":"60004.png","x":-23},{"y":-137,"res":"60005.png","x":-36},{"y":-108,"res":"60006.png","x":-49}],"frameRate":15}}}